{
  "config_id": "ep20_spcurrent_varsreduced",
  "variable_set": "reduced",
  "mode": "constrained",
  "constraint_mode": "native_constrained",
  "epochs": 20,
  "threshold": 0.35,
  "sparsity_strength": "current",
  "l1_lambda": 0.05,
  "mean_f1": 0.4688637730251908,
  "std_f1": 0.08291217079558762,
  "mean_precision": 0.5575341406585518,
  "mean_recall": 0.4075471698113208,
  "mean_shd": 48.2,
  "std_shd": 5.019960159204453,
  "mean_edge_count": 38.4,
  "std_edge_count": 5.727128425310541,
  "mean_violations": 0.0,
  "mean_runtime": 22.91386,
  "successful_runs": 5,
  "failed_runs": 0,
  "timed_out_runs": 0,
  "success_rate": 1.0,
  "acceptable": true,
  "selection_rank": "",
  "mean_f1_unconstrained": 0.26306674889320075,
  "mean_shd_unconstrained": 63.4,
  "mean_edge_count_unconstrained": 33.2,
  "mean_runtime_unconstrained": 22.78422,
  "f1_preserved_or_improved": true,
  "shd_reduced": true,
  "edge_count_deviation": 14.600000000000001,
  "decision_note": "Selected among acceptable configurations using synthetic data only.",
  "true_synthetic_edge_count": 53.0,
  "native_required_supported": true,
  "backend": "causica"
}